setup.py
enCompress.egg-info/PKG-INFO
enCompress.egg-info/SOURCES.txt
enCompress.egg-info/dependency_links.txt
enCompress.egg-info/entry_points.txt
enCompress.egg-info/requires.txt
enCompress.egg-info/top_level.txt
encode_compress/__init__.py
encode_compress/enCrypt.py