Metadata-Version: 1.2
Name: enCompress
Version: 1.4
Summary: Creates a password protected compressed file
Home-page: UNKNOWN
Author: UNKNOWN
Author-email: UNKNOWN
License: UNKNOWN
Platform: UNKNOWN
Requires-Python: >=3
